atmos/__init__.py
atmos/client.py
atmos/exceptions.py
atmos/models.py
atmos/utils.py
atmos_payment-0.1.0.dist-info/licenses/LICENSE
tests/__init__.py
tests/test_callback.py
tests/test_client.py
tests/test_models.py
tests/test_utils.py
atmos_payment-0.1.0.dist-info/METADATA
atmos_payment-0.1.0.dist-info/WHEEL
atmos_payment-0.1.0.dist-info/top_level.txt
atmos_payment-0.1.0.dist-info/RECORD
