Metadata-Version: 2.4
Name: atmos-payment
Version: 0.1.0
Summary: A Python library for the Atmos payment provider
Home-page: https://github.com/Muhammadali-Akbarov/atmos-pkg
Author: Muhammadali-Akbarov
Author-email: muhammadali17abc@gmail.com
Project-URL: Bug Reports, https://github.com/Muhammadali-Akbarov/atmos-pkg/issues
Project-URL: Source, https://github.com/Muhammadali-Akbarov/atmos-pkg
Project-URL: Documentation, https://github.com/Muhammadali-Akbarov/atmos-pkg
Keywords: payment,atmos,api,client
Classifier: Development Status :: 4 - Beta
Classifier: Intended Audience :: Developers
Classifier: License :: OSI Approved :: MIT License
Classifier: Programming Language :: Python :: 3
Classifier: Programming Language :: Python :: 3.7
Classifier: Programming Language :: Python :: 3.8
Classifier: Programming Language :: Python :: 3.9
Classifier: Programming Language :: Python :: 3.10
Classifier: Programming Language :: Python :: 3.11
Classifier: Programming Language :: Python :: 3.12
Classifier: Topic :: Software Development :: Libraries :: Python Modules
Requires-Python: >=3.7
License-File: LICENSE
Requires-Dist: requests>=2.25.0
Dynamic: author
Dynamic: author-email
Dynamic: classifier
Dynamic: description
Dynamic: description-content-type
Dynamic: home-page
Dynamic: keywords
Dynamic: license-file
Dynamic: project-url
Dynamic: requires-dist
Dynamic: requires-python
Dynamic: summary
